formal/__init__.py
formal/database.py
formal/exceptions.py
formal/model_base.py
formal/model_mongodb.py
formal/model_sqlalchemy.py
formal/scm_version.py
formal-0.6.3.data/scripts/sqlconverter
formal-0.6.3.dist-info/LICENSE
formal-0.6.3.dist-info/METADATA
formal-0.6.3.dist-info/WHEEL
formal-0.6.3.dist-info/top_level.txt
formal-0.6.3.dist-info/RECORD
